LICENSE
MANIFEST.in
README.md
setup.cfg
setup.py
xdi_pandas/__init__.py
xdi_pandas/core.py
xdi_pandas/fn_utils.py
xdi_pandas/xdi_types.py
xdi_pandas.egg-info/PKG-INFO
xdi_pandas.egg-info/SOURCES.txt
xdi_pandas.egg-info/dependency_links.txt
xdi_pandas.egg-info/requires.txt
xdi_pandas.egg-info/top_level.txt