Metadata-Version: 1.1
Name: xdi-pandas
Version: 0.2.0
Summary: Read XDI files to Pandas dataframes
Home-page: https://github.com/ptbrowne/xdi-pandas
Author: Patrick Browne
Author-email: pt.browne@gmail.com
License: MIT
